otlmow_template/SubsetTemplateCreator.py
otlmow_template/Exceptions/MissingTypeUriException.py
otlmow_template-1.9.dist-info/licenses/LICENSE
otlmow_template-1.9.dist-info/METADATA
otlmow_template-1.9.dist-info/WHEEL
otlmow_template-1.9.dist-info/top_level.txt
otlmow_template-1.9.dist-info/RECORD
