Metadata-Version: 2.4
Name: otlmow_template
Version: 1.9
Author-email: David Vlaminck <david.vlaminck@mow.vlaanderen.be>, Jasper Berton <jasperberton1@telenet.be>
License:                     GNU GENERAL PUBLIC LICENSE
Project-URL: Homepage, https://github.com/davidvlaminck/OTLMOW-Template
Project-URL: Bug Tracker, https://github.com/davidvlaminck/OTLMOW-Template/issues
Classifier: Programming Language :: Python :: 3
Classifier: Programming Language :: Python :: 3.9
Classifier: Programming Language :: Python :: 3.10
Classifier: Programming Language :: Python :: 3.11
Classifier: Programming Language :: Python :: 3.12
Classifier: Programming Language :: Python :: 3.13
Classifier: Operating System :: OS Independent
Classifier: Development Status :: 5 - Production/Stable
Classifier: Environment :: Console
Classifier: Intended Audience :: Developers
Classifier: Intended Audience :: Information Technology
Classifier: License :: OSI Approved :: GNU General Public License v3 (GPLv3)
Classifier: Natural Language :: Dutch
Classifier: Topic :: Software Development
Classifier: Topic :: Software Development :: Libraries :: Python Modules
Classifier: Topic :: Software Development :: Quality Assurance
Requires-Python: >=3.9
License-File: LICENSE
Requires-Dist: otlmow-converter>=1.14
Requires-Dist: otlmow-modelbuilder>=0.37
Provides-Extra: test
Requires-Dist: pytest; extra == "test"
Requires-Dist: pytest-cov; extra == "test"
Requires-Dist: pytest-subtests; extra == "test"
Requires-Dist: pytest-timeout; extra == "test"
Requires-Dist: pytest-asyncio; extra == "test"
Dynamic: license-file
